windmillclient/__init__.py
windmillclient/client/__init__.py
windmillclient/client/mock.py
windmillclient/client/windmill_client.py
pywindmill-1.3.14.dist-info/METADATA
pywindmill-1.3.14.dist-info/WHEEL
pywindmill-1.3.14.dist-info/top_level.txt
pywindmill-1.3.14.dist-info/RECORD
