Metadata-Version: 2.1
Name: pywindmill
Version: 1.3.14
Summary: sdk in python for windmill client
Home-page: http://www.ai.com
Author: yangtingyu01
License: MIT
Classifier: Programming Language :: Python
Classifier: Programming Language :: Python :: 3
Classifier: Programming Language :: Python :: 3.7
Classifier: Programming Language :: Python :: 3.8
Classifier: Programming Language :: Python :: 3.9
Requires-Python: >=3.6
Requires-Dist: bce-python-sdk ==0.8.87
Requires-Dist: multidict ==6.0.4
Requires-Dist: windmill-device ==1.0.0.19
Requires-Dist: windmill-artifact ==1.0.0.27
Requires-Dist: windmill-train ==1.0.0.22
Requires-Dist: windmill-workspace ==1.0.0.2
Requires-Dist: windmill-model ==1.0.0.60
Requires-Dist: windmill-compute ==1.0.0.36
Requires-Dist: windmill-endpoint ==1.0.0.24
Requires-Dist: windmill-usersetting ==1.0.0.5
Requires-Dist: bce-internal-sdk ==1.0.0.15
Requires-Dist: jobv1 ==0.0.3
Requires-Dist: graph-service
Requires-Dist: pydantic
Requires-Dist: pyyaml
Requires-Dist: bcelogger
Requires-Dist: flask
